cf_proxy/__init__.py
cf_proxy/async_client.py
cf_proxy/client.py
cf_proxy/common.py
cf_proxy/sync_client.py
cf_proxy-0.2.0.dist-info/METADATA
cf_proxy-0.2.0.dist-info/WHEEL
cf_proxy-0.2.0.dist-info/licenses/LICENSE
cf_proxy-0.2.0.dist-info/RECORD
