Metadata-Version: 2.4
Name: cf_proxy
Version: 0.2.0
Summary: Python package utilizing Cloudflare Workers to proxy requests
Project-URL: Source, https://github.com/kevintsoii/cf_proxy
Author-email: kevintsoii <kevin.tsoi44@gmail.com>
License: MIT License
License-File: LICENSE
Classifier: Operating System :: OS Independent
Classifier: Programming Language :: Python :: 3
Requires-Python: >=3.8
Requires-Dist: httpx>=0.24.0
